xiaoxiong/__init__.py
xiaoxiong/oh_bear.py
xiaoxiong-0.0.2.dist-info/LICENSE
xiaoxiong-0.0.2.dist-info/METADATA
xiaoxiong-0.0.2.dist-info/WHEEL
xiaoxiong-0.0.2.dist-info/top_level.txt
xiaoxiong-0.0.2.dist-info/RECORD
