Metadata-Version: 2.1
Name: xiaoxiong
Version: 0.0.2
Summary: Oh Bear !
Home-page: https://gitee.com/ly_love_ly/xiaoxiong
Author: ygg
Author-email: ygg@zut.edu.cn
License: UNKNOWN
Platform: UNKNOWN
Classifier: Programming Language :: Python :: 3
Classifier: License :: OSI Approved :: MIT License
Classifier: Operating System :: OS Independent
